Metadata-Version: 2.1
Name: dbt-databend-cloud
Version: 1.8.1
Summary: The Databend adapter plugin for dbt
Home-page: https://github.com/databendcloud/dbt-databend.git
Author: Databend Cloud Team
Author-email: zhangzhihan@datafuselabs.com
Classifier: Development Status :: 5 - Production/Stable
Classifier: License :: OSI Approved :: Apache Software License
Classifier: Operating System :: Microsoft :: Windows
Classifier: Operating System :: MacOS :: MacOS X
Classifier: Operating System :: POSIX :: Linux
Classifier: Programming Language :: Python :: 3.10
Classifier: Programming Language :: Python :: 3.11
Classifier: Programming Language :: Python :: 3.12
Requires-Python: >=3.8
License-File: LICENSE
Requires-Dist: dbt-common <2.0,>=1.0.4
Requires-Dist: dbt-adapters <2.0,>=1.1.1
Requires-Dist: dbt-core >=1.8.0
Requires-Dist: agate
Requires-Dist: databend-sqlalchemy ~=0.3.2
